// class version 61.0 (61)
// access flags 0x21
public class Bank/Loan {

  // compiled from: Loan.java
  // access flags 0x19
  public final static INNERCLASS java/lang/invoke/MethodHandles$Lookup java/lang/invoke/MethodHandles Lookup

  // access flags 0x1
  public <init>()V
   L0
    LINENUMBER 5 L0
    ALOAD 0
    INVOKESPECIAL java/lang/Object.<init> ()V
    RETURN
   L1
    LOCALVARIABLE this LBank/Loan; L0 L1 0
    MAXSTACK = 1
    MAXLOCALS = 1

  // access flags 0x9
  public static main([Ljava/lang/String;)V
   L0
    LINENUMBER 7 L0
    NEW java/util/Scanner
    DUP
    GETSTATIC java/lang/System.in : Ljava/io/InputStream;
    INVOKESPECIAL java/util/Scanner.<init> (Ljava/io/InputStream;)V
    ASTORE 1
   L1
    LINENUMBER 9 L1
    GETSTATIC java/lang/System.out : Ljava/io/PrintStream;
    LDC "Enter debt value (in euros): "
    INVOKEVIRTUAL java/io/PrintStream.print (Ljava/lang/String;)V
   L2
    LINENUMBER 10 L2
    ALOAD 1
    INVOKEVIRTUAL java/util/Scanner.nextDouble ()D
    DSTORE 2
   L3
    LINENUMBER 12 L3
    GETSTATIC java/lang/System.out : Ljava/io/PrintStream;
    LDC "Enter interest rate (percentage): "
    INVOKEVIRTUAL java/io/PrintStream.print (Ljava/lang/String;)V
   L4
    LINENUMBER 13 L4
    ALOAD 1
    INVOKEVIRTUAL java/util/Scanner.nextDouble ()D
    DSTORE 4
   L5
    LINENUMBER 15 L5
    GETSTATIC java/lang/System.out : Ljava/io/PrintStream;
    LDC "Enter payback duration (months): "
    INVOKEVIRTUAL java/io/PrintStream.print (Ljava/lang/String;)V
   L6
    LINENUMBER 16 L6
    ALOAD 1
    INVOKEVIRTUAL java/util/Scanner.nextInt ()I
    ISTORE 6
   L7
    LINENUMBER 18 L7
    DLOAD 2
    DLOAD 4
    ILOAD 6
    INVOKESTATIC Bank/Loan.calculateMonthlyRate (DDI)D
    DSTORE 7
   L8
    LINENUMBER 19 L8
    DLOAD 2
    DLOAD 7
    INVOKESTATIC Bank/Loan.calculateNumberOfRates (DD)I
    ISTORE 9
   L9
    LINENUMBER 20 L9
    DLOAD 2
    ILOAD 9
    DLOAD 7
    INVOKESTATIC Bank/Loan.calculateOverallDebt (DID)D
    DSTORE 10
   L10
    LINENUMBER 22 L10
    GETSTATIC java/lang/System.out : Ljava/io/PrintStream;
    DLOAD 7
    INVOKEDYNAMIC makeConcatWithConstants(D)Ljava/lang/String; [
      // handle kind 0x6 : INVOKESTATIC
      java/lang/invoke/StringConcatFactory.makeConcatWithConstants(Ljava/lang/invoke/MethodHandles$Lookup;Ljava/lang/String;Ljava/lang/invoke/MethodType;Ljava/lang/String;[Ljava/lang/Object;)Ljava/lang/invoke/CallSite;
      // arguments:
      "Monthly Rate: \u0001"
    ]
    INVOKEVIRTUAL java/io/PrintStream.println (Ljava/lang/String;)V
   L11
    LINENUMBER 23 L11
    GETSTATIC java/lang/System.out : Ljava/io/PrintStream;
    ILOAD 9
    INVOKEDYNAMIC makeConcatWithConstants(I)Ljava/lang/String; [
      // handle kind 0x6 : INVOKESTATIC
      java/lang/invoke/StringConcatFactory.makeConcatWithConstants(Ljava/lang/invoke/MethodHandles$Lookup;Ljava/lang/String;Ljava/lang/invoke/MethodType;Ljava/lang/String;[Ljava/lang/Object;)Ljava/lang/invoke/CallSite;
      // arguments:
      "Number of Rates: \u0001"
    ]
    INVOKEVIRTUAL java/io/PrintStream.println (Ljava/lang/String;)V
   L12
    LINENUMBER 24 L12
    GETSTATIC java/lang/System.out : Ljava/io/PrintStream;
    DLOAD 10
    INVOKEDYNAMIC makeConcatWithConstants(D)Ljava/lang/String; [
      // handle kind 0x6 : INVOKESTATIC
      java/lang/invoke/StringConcatFactory.makeConcatWithConstants(Ljava/lang/invoke/MethodHandles$Lookup;Ljava/lang/String;Ljava/lang/invoke/MethodType;Ljava/lang/String;[Ljava/lang/Object;)Ljava/lang/invoke/CallSite;
      // arguments:
      "Overall Debt: \u0001"
    ]
    INVOKEVIRTUAL java/io/PrintStream.println (Ljava/lang/String;)V
   L13
    LINENUMBER 25 L13
    RETURN
   L14
    LOCALVARIABLE args [Ljava/lang/String; L0 L14 0
    LOCALVARIABLE scanner Ljava/util/Scanner; L1 L14 1
    LOCALVARIABLE debt D L3 L14 2
    LOCALVARIABLE interestRate D L5 L14 4
    LOCALVARIABLE duration I L7 L14 6
    LOCALVARIABLE monthlyRate D L8 L14 7
    LOCALVARIABLE numberOfRates I L9 L14 9
    LOCALVARIABLE overallDebt D L10 L14 10
    MAXSTACK = 5
    MAXLOCALS = 12

  // access flags 0x9
  public static calculateMonthlyRate(DDI)D
   L0
    LINENUMBER 28 L0
    DLOAD 2
    LDC 100.0
    DDIV
    LDC 12.0
    DDIV
    DSTORE 5
   L1
    LINENUMBER 29 L1
    DLOAD 0
    DLOAD 5
    DMUL
    DCONST_1
    DCONST_1
    DLOAD 5
    DADD
    ILOAD 4
    INEG
    I2D
    INVOKESTATIC java/lang/Math.pow (DD)D
    DSUB
    DDIV
    DRETURN
   L2
    LOCALVARIABLE debt D L0 L2 0
    LOCALVARIABLE interestRate D L0 L2 2
    LOCALVARIABLE duration I L0 L2 4
    LOCALVARIABLE monthlyInterestRate D L1 L2 5
    MAXSTACK = 8
    MAXLOCALS = 7

  // access flags 0x9
  public static calculateNumberOfRates(DD)I
   L0
    LINENUMBER 33 L0
    DLOAD 0
    DLOAD 2
    DMUL
    INVOKESTATIC java/lang/Math.ceil (D)D
    D2I
    IRETURN
   L1
    LOCALVARIABLE debt D L0 L1 0
    LOCALVARIABLE monthlyRate D L0 L1 2
    MAXSTACK = 4
    MAXLOCALS = 4

  // access flags 0x9
  public static calculateOverallDebt(DID)D
   L0
    LINENUMBER 37 L0
    DLOAD 0
    ILOAD 2
    I2D
    DLOAD 3
    DMUL
    DADD
    DRETURN
   L1
    LOCALVARIABLE debt D L0 L1 0
    LOCALVARIABLE numberOfRates I L0 L1 2
    LOCALVARIABLE monthlyRate D L0 L1 3
    MAXSTACK = 6
    MAXLOCALS = 5
}

